json_pattern_validator/__init__.py
json_pattern_validator/json_validator.py
json_pattern_validator/validators.py
json_pattern_validator-0.1.dist-info/METADATA
json_pattern_validator-0.1.dist-info/WHEEL
json_pattern_validator-0.1.dist-info/top_level.txt
json_pattern_validator-0.1.dist-info/RECORD
