Metadata-Version: 2.1
Name: json-pattern-validator
Version: 0.1
Summary: Utility for evaluate matching json with a template
Home-page: https://github.com/dmalisani/json_pattern_validator
Author: Daniel Malisani
Author-email: dmalisani@gmail.com
License: UNKNOWN
Keywords: json,schema,validation,validator,payload
Platform: UNKNOWN
Classifier: Development Status :: 3 - Alpha
Classifier: License :: OSI Approved :: GNU General Public License (GPL)
Classifier: Programming Language :: Python :: 3
Classifier: Programming Language :: Python :: 3.8
